dynamic_settings/__init__.py
dynamic_settings/dynamic_settings.py
dynamic_settings/errors.py
dynamic_settings/types.py
dynamic_settings-0.1.0.dist-info/METADATA
dynamic_settings-0.1.0.dist-info/WHEEL
dynamic_settings-0.1.0.dist-info/RECORD
