Metadata-Version: 2.3
Name: dynamic-settings
Version: 0.1.0
Summary: Client for dynamic settings service https://github.com/MarkAntipin/dynamic-settings
Author: Mark Antipin
Author-email: mr.antipin@gmail.com
Requires-Python: >=3.9,<4.0
Classifier: Programming Language :: Python :: 3
Classifier: Programming Language :: Python :: 3.9
Classifier: Programming Language :: Python :: 3.10
Classifier: Programming Language :: Python :: 3.11
Classifier: Programming Language :: Python :: 3.12
Classifier: Programming Language :: Python :: 3.13
